<annotation>
	<folder>Foto Traffic Sign 2</folder>
	<filename>2020-10-05-055306.jpg</filename>
	<path>D:\OneDrive - Universitas Diponegoro\Kuliah\Lesson\7th Semester\Tugas Akhir - AGV\Traffic Sign\Foto Traffic Sign 2\2020-10-05-055306.jpg</path>
	<source>
		<database>Unknown</database>
	</source>
	<size>
		<width>960</width>
		<height>544</height>
		<depth>3</depth>
	</size>
	<segmented>0</segmented>
	<object>
		<name>Red Traffic Light</name>
		<pose>Unspecified</pose>
		<truncated>0</truncated>
		<difficult>0</difficult>
		<bndbox>
			<xmin>26</xmin>
			<ymin>211</ymin>
			<xmax>103</xmax>
			<ymax>387</ymax>
		</bndbox>
	</object>
	<object>
		<name>Green Traffic Light</name>
		<pose>Unspecified</pose>
		<truncated>0</truncated>
		<difficult>0</difficult>
		<bndbox>
			<xmin>163</xmin>
			<ymin>215</ymin>
			<xmax>231</xmax>
			<ymax>380</ymax>
		</bndbox>
	</object>
	<object>
		<name>Slow</name>
		<pose>Unspecified</pose>
		<truncated>0</truncated>
		<difficult>0</difficult>
		<bndbox>
			<xmin>294</xmin>
			<ymin>288</ymin>
			<xmax>476</xmax>
			<ymax>338</ymax>
		</bndbox>
	</object>
	<object>
		<name>Fast</name>
		<pose>Unspecified</pose>
		<truncated>0</truncated>
		<difficult>0</difficult>
		<bndbox>
			<xmin>514</xmin>
			<ymin>285</ymin>
			<xmax>663</xmax>
			<ymax>332</ymax>
		</bndbox>
	</object>
	<object>
		<name>Stop Sign</name>
		<pose>Unspecified</pose>
		<truncated>0</truncated>
		<difficult>0</difficult>
		<bndbox>
			<xmin>707</xmin>
			<ymin>266</ymin>
			<xmax>784</xmax>
			<ymax>348</ymax>
		</bndbox>
	</object>
	<object>
		<name>Person</name>
		<pose>Unspecified</pose>
		<truncated>0</truncated>
		<difficult>0</difficult>
		<bndbox>
			<xmin>816</xmin>
			<ymin>190</ymin>
			<xmax>904</xmax>
			<ymax>399</ymax>
		</bndbox>
	</object>
</annotation>
